pygamehelper/__init__.py
pygamehelper/pygamehelper.py
pygamehelper-0.0.1.dist-info/LICENSE
pygamehelper-0.0.1.dist-info/METADATA
pygamehelper-0.0.1.dist-info/WHEEL
pygamehelper-0.0.1.dist-info/top_level.txt
pygamehelper-0.0.1.dist-info/RECORD
