Metadata-Version: 2.1
Name: pygamehelper
Version: 0.0.1
Summary: Helps you to scale,rotate and display text on the pygame window 
Home-page: UNKNOWN
Author: Asher Thomas Abraham
Author-email: achutomonline@gmail.com
License: UNKNOWN
Keywords: python,text,rotate,pygame,scale
Platform: UNKNOWN
Classifier: Development Status :: 1 - Planning
Classifier: Intended Audience :: Developers
Classifier: Programming Language :: Python :: 3
Classifier: Operating System :: Unix
Classifier: Operating System :: MacOS :: MacOS X
Classifier: Operating System :: Microsoft :: Windows
Requires-Dist: pygame
